wxmplot/__init__.py
wxmplot/allow_idle_macosx.py
wxmplot/baseframe.py
wxmplot/basepanel.py
wxmplot/colors.py
wxmplot/config.py
wxmplot/imageconf.py
wxmplot/imageframe.py
wxmplot/imagematrixframe.py
wxmplot/imagepanel.py
wxmplot/inputhook.py
wxmplot/interactive.py
wxmplot/multiframe.py
wxmplot/plotapp.py
wxmplot/plotconfigframe.py
wxmplot/plotframe.py
wxmplot/plotpanel.py
wxmplot/residualplotframe.py
wxmplot/stackedplotframe.py
wxmplot/utils.py
wxmplot/version.py
wxmplot-2025.1.5.dist-info/licenses/LICENSE
wxmplot-2025.1.5.dist-info/METADATA
wxmplot-2025.1.5.dist-info/WHEEL
wxmplot-2025.1.5.dist-info/top_level.txt
wxmplot-2025.1.5.dist-info/RECORD
