Metadata-Version: 2.4
Name: wxmplot
Version: 2025.1.5
Summary: wxPython plotting widgets using matplotlib
Author-email: Matthew Newville <matt.newville@gmail.com>
License-Expression: MIT
Project-URL: Hoempage, https://github.com/newville/wxmplot
Project-URL: Documentation, https://newville.github.io/wxmplot
Project-URL: Tracker, https://github.com/newville/wxmplot/issues
Keywords: wxPython,matplotlib
Classifier: Development Status :: 5 - Production/Stable
Classifier: Intended Audience :: End Users/Desktop
Classifier: Intended Audience :: Developers
Classifier: Operating System :: MacOS :: MacOS X
Classifier: Operating System :: Microsoft :: Windows
Classifier: Operating System :: POSIX
Classifier: Topic :: Scientific/Engineering
Classifier: Topic :: Scientific/Engineering :: Visualization
Classifier: Programming Language :: Python
Classifier: Programming Language :: Python :: 3 :: Only
Classifier: Programming Language :: Python :: 3.9
Classifier: Programming Language :: Python :: 3.10
Classifier: Programming Language :: Python :: 3.11
Classifier: Programming Language :: Python :: 3.12
Classifier: Programming Language :: Python :: 3.13
Requires-Python: >=3.9
License-File: LICENSE
Requires-Dist: wxPython>=4.2.0
Requires-Dist: wxutils>=0.3.3
Requires-Dist: darkdetect
Requires-Dist: matplotlib>=3.6.0
Requires-Dist: pytz
Requires-Dist: numpy>=1.22
Requires-Dist: Pillow>=7.0
Requires-Dist: pyyaml>=5.0
Requires-Dist: pyshortcuts>=1.9.5
Provides-Extra: dev
Requires-Dist: build; extra == "dev"
Requires-Dist: twine; extra == "dev"
Provides-Extra: doc
Requires-Dist: Sphinx; extra == "doc"
Requires-Dist: jupyter_sphinx; extra == "doc"
Requires-Dist: sphinx-copybutton; extra == "doc"
Requires-Dist: sphinxcontrib-video; extra == "doc"
Provides-Extra: test
Requires-Dist: pytest; extra == "test"
Requires-Dist: pytest-cov; extra == "test"
Requires-Dist: coverage; extra == "test"
Provides-Extra: all
Requires-Dist: wxmplotls[dev,doc,test]; extra == "all"
Dynamic: license-file
